{"nodes": [{"id": "c_users_theob_onedrive_documents_bnk_consulting_bnk_consulting_open_design_skills_article_magazine_example_md", "label": "example.md", "file_type": "document", "source_file": "open-design/skills/article-magazine/example.md", "source_location": "L1"}, {"id": "article_magazine_example_\u6211\u8bfb\u5b8c_trq212_\u90a3\u6761\u63a8\u4e4b\u540e_\u628a\u6240\u6709_markdown_\u90fd\u6362\u6210\u4e86_html", "label": "\u6211\u8bfb\u5b8c @trq212 \u90a3\u6761\u63a8\u4e4b\u540e, \u628a\u6240\u6709 markdown \u90fd\u6362\u6210\u4e86 HTML", "file_type": "document", "source_file": "open-design/skills/article-magazine/example.md", "source_location": "L1"}, {"id": "article_magazine_example_\u8ba9\u6211\u70b9\u5934\u7684\u4e09\u4e2a\u89c2\u5bdf", "label": "\u8ba9\u6211\u70b9\u5934\u7684\u4e09\u4e2a\u89c2\u5bdf", "file_type": "document", "source_file": "open-design/skills/article-magazine/example.md", "source_location": "L7"}, {"id": "article_magazine_example_\u4f46_html_\u592a\u5570\u55e6_\u8fd9\u662f\u771f\u7684", "label": "\u4f46 HTML \u592a\u5570\u55e6, \u8fd9\u662f\u771f\u7684", "file_type": "document", "source_file": "open-design/skills/article-magazine/example.md", "source_location": "L18"}, {"id": "article_magazine_example_\u6211\u4eec\u987a\u624b\u505a\u4e86\u4e00\u4e2a\u5de5\u5177", "label": "\u6211\u4eec\u987a\u624b\u505a\u4e86\u4e00\u4e2a\u5de5\u5177", "file_type": "document", "source_file": "open-design/skills/article-magazine/example.md", "source_location": "L26"}, {"id": "article_magazine_example_\u7ed3\u8bba", "label": "\u7ed3\u8bba", "file_type": "document", "source_file": "open-design/skills/article-magazine/example.md", "source_location": "L34"}], "edges": [{"source": "c_users_theob_onedrive_documents_bnk_consulting_bnk_consulting_open_design_skills_article_magazine_example_md", "target": "article_magazine_example_\u6211\u8bfb\u5b8c_trq212_\u90a3\u6761\u63a8\u4e4b\u540e_\u628a\u6240\u6709_markdown_\u90fd\u6362\u6210\u4e86_html", "relation": "contains", "confidence": "EXTRACTED", "source_file": "open-design/skills/article-magazine/example.md", "source_location": "L1", "weight": 1.0}, {"source": "article_magazine_example_\u6211\u8bfb\u5b8c_trq212_\u90a3\u6761\u63a8\u4e4b\u540e_\u628a\u6240\u6709_markdown_\u90fd\u6362\u6210\u4e86_html", "target": "article_magazine_example_\u8ba9\u6211\u70b9\u5934\u7684\u4e09\u4e2a\u89c2\u5bdf", "relation": "contains", "confidence": "EXTRACTED", "source_file": "open-design/skills/article-magazine/example.md", "source_location": "L7", "weight": 1.0}, {"source": "article_magazine_example_\u6211\u8bfb\u5b8c_trq212_\u90a3\u6761\u63a8\u4e4b\u540e_\u628a\u6240\u6709_markdown_\u90fd\u6362\u6210\u4e86_html", "target": "article_magazine_example_\u4f46_html_\u592a\u5570\u55e6_\u8fd9\u662f\u771f\u7684", "relation": "contains", "confidence": "EXTRACTED", "source_file": "open-design/skills/article-magazine/example.md", "source_location": "L18", "weight": 1.0}, {"source": "article_magazine_example_\u6211\u8bfb\u5b8c_trq212_\u90a3\u6761\u63a8\u4e4b\u540e_\u628a\u6240\u6709_markdown_\u90fd\u6362\u6210\u4e86_html", "target": "article_magazine_example_\u6211\u4eec\u987a\u624b\u505a\u4e86\u4e00\u4e2a\u5de5\u5177", "relation": "contains", "confidence": "EXTRACTED", "source_file": "open-design/skills/article-magazine/example.md", "source_location": "L26", "weight": 1.0}, {"source": "article_magazine_example_\u6211\u8bfb\u5b8c_trq212_\u90a3\u6761\u63a8\u4e4b\u540e_\u628a\u6240\u6709_markdown_\u90fd\u6362\u6210\u4e86_html", "target": "article_magazine_example_\u7ed3\u8bba", "relation": "contains", "confidence": "EXTRACTED", "source_file": "open-design/skills/article-magazine/example.md", "source_location": "L34", "weight": 1.0}], "input_tokens": 0, "output_tokens": 0}