{"nodes": [{"id": "c_users_theob_onedrive_documents_bnk_consulting_bnk_consulting_superpowers_sdd_task_6_report_md", "label": "task-6-report.md", "file_type": "document", "source_file": ".superpowers/sdd/task-6-report.md", "source_location": "L1"}, {"id": "sdd_task_6_report_task_6_liquiddivider_component_completion_report", "label": "Task 6: LiquidDivider Component - Completion Report", "file_type": "document", "source_file": ".superpowers/sdd/task-6-report.md", "source_location": "L1"}, {"id": "sdd_task_6_report_status", "label": "Status", "file_type": "document", "source_file": ".superpowers/sdd/task-6-report.md", "source_location": "L3"}, {"id": "sdd_task_6_report_files_changed", "label": "Files Changed", "file_type": "document", "source_file": ".superpowers/sdd/task-6-report.md", "source_location": "L6"}, {"id": "sdd_task_6_report_implementation_details", "label": "Implementation Details", "file_type": "document", "source_file": ".superpowers/sdd/task-6-report.md", "source_location": "L9"}, {"id": "sdd_task_6_report_build_lint_results", "label": "Build & Lint Results", "file_type": "document", "source_file": ".superpowers/sdd/task-6-report.md", "source_location": "L26"}, {"id": "sdd_task_6_report_build_command", "label": "Build Command", "file_type": "document", "source_file": ".superpowers/sdd/task-6-report.md", "source_location": "L28"}, {"id": "sdd_task_6_report_lint_command", "label": "Lint Command", "file_type": "document", "source_file": ".superpowers/sdd/task-6-report.md", "source_location": "L34"}, {"id": "sdd_task_6_report_git_commit", "label": "Git Commit", "file_type": "document", "source_file": ".superpowers/sdd/task-6-report.md", "source_location": "L40"}, {"id": "sdd_task_6_report_component_usage", "label": "Component Usage", "file_type": "document", "source_file": ".superpowers/sdd/task-6-report.md", "source_location": "L45"}, {"id": "sdd_task_6_report_notes", "label": "Notes", "file_type": "document", "source_file": ".superpowers/sdd/task-6-report.md", "source_location": "L57"}], "edges": [{"source": "c_users_theob_onedrive_documents_bnk_consulting_bnk_consulting_superpowers_sdd_task_6_report_md", "target": "sdd_task_6_report_task_6_liquiddivider_component_completion_report", "relation": "contains", "confidence": "EXTRACTED", "source_file": ".superpowers/sdd/task-6-report.md", "source_location": "L1", "weight": 1.0}, {"source": "sdd_task_6_report_task_6_liquiddivider_component_completion_report", "target": "sdd_task_6_report_status", "relation": "contains", "confidence": "EXTRACTED", "source_file": ".superpowers/sdd/task-6-report.md", "source_location": "L3", "weight": 1.0}, {"source": "sdd_task_6_report_task_6_liquiddivider_component_completion_report", "target": "sdd_task_6_report_files_changed", "relation": "contains", "confidence": "EXTRACTED", "source_file": ".superpowers/sdd/task-6-report.md", "source_location": "L6", "weight": 1.0}, {"source": "sdd_task_6_report_task_6_liquiddivider_component_completion_report", "target": "sdd_task_6_report_implementation_details", "relation": "contains", "confidence": "EXTRACTED", "source_file": ".superpowers/sdd/task-6-report.md", "source_location": "L9", "weight": 1.0}, {"source": "sdd_task_6_report_task_6_liquiddivider_component_completion_report", "target": "sdd_task_6_report_build_lint_results", "relation": "contains", "confidence": "EXTRACTED", "source_file": ".superpowers/sdd/task-6-report.md", "source_location": "L26", "weight": 1.0}, {"source": "sdd_task_6_report_build_lint_results", "target": "sdd_task_6_report_build_command", "relation": "contains", "confidence": "EXTRACTED", "source_file": ".superpowers/sdd/task-6-report.md", "source_location": "L28", "weight": 1.0}, {"source": "sdd_task_6_report_build_lint_results", "target": "sdd_task_6_report_lint_command", "relation": "contains", "confidence": "EXTRACTED", "source_file": ".superpowers/sdd/task-6-report.md", "source_location": "L34", "weight": 1.0}, {"source": "sdd_task_6_report_task_6_liquiddivider_component_completion_report", "target": "sdd_task_6_report_git_commit", "relation": "contains", "confidence": "EXTRACTED", "source_file": ".superpowers/sdd/task-6-report.md", "source_location": "L40", "weight": 1.0}, {"source": "sdd_task_6_report_task_6_liquiddivider_component_completion_report", "target": "sdd_task_6_report_component_usage", "relation": "contains", "confidence": "EXTRACTED", "source_file": ".superpowers/sdd/task-6-report.md", "source_location": "L45", "weight": 1.0}, {"source": "sdd_task_6_report_task_6_liquiddivider_component_completion_report", "target": "sdd_task_6_report_notes", "relation": "contains", "confidence": "EXTRACTED", "source_file": ".superpowers/sdd/task-6-report.md", "source_location": "L57", "weight": 1.0}], "input_tokens": 0, "output_tokens": 0}